odoo/addons/stock_picking_package_preparation/README.rst
odoo/addons/stock_picking_package_preparation/__init__.py
odoo/addons/stock_picking_package_preparation/__manifest__.py
odoo/addons/stock_picking_package_preparation/i18n/de.po
odoo/addons/stock_picking_package_preparation/i18n/en.po
odoo/addons/stock_picking_package_preparation/i18n/es.po
odoo/addons/stock_picking_package_preparation/i18n/fr.po
odoo/addons/stock_picking_package_preparation/i18n/it.po
odoo/addons/stock_picking_package_preparation/i18n/nl_NL.po
odoo/addons/stock_picking_package_preparation/i18n/sl.po
odoo/addons/stock_picking_package_preparation/i18n/stock_picking_package_preparation.pot
odoo/addons/stock_picking_package_preparation/models/__init__.py
odoo/addons/stock_picking_package_preparation/models/stock_picking_package_preparation.py
odoo/addons/stock_picking_package_preparation/readme/CONTRIBUTORS.rst
odoo/addons/stock_picking_package_preparation/readme/DESCRIPTION.rst
odoo/addons/stock_picking_package_preparation/readme/ROADMAP.rst
odoo/addons/stock_picking_package_preparation/readme/USAGE.rst
odoo/addons/stock_picking_package_preparation/security/ir.model.access.csv
odoo/addons/stock_picking_package_preparation/security/package_preparation_security.xml
odoo/addons/stock_picking_package_preparation/static/description/icon.png
odoo/addons/stock_picking_package_preparation/static/description/index.html
odoo/addons/stock_picking_package_preparation/tests/__init__.py
odoo/addons/stock_picking_package_preparation/tests/test_package_preparation.py
odoo/addons/stock_picking_package_preparation/views/stock_picking_package_preparation_view.xml
odoo11_addon_stock_picking_package_preparation-11.0.1.0.0.99.dev14.dist-info/METADATA
odoo11_addon_stock_picking_package_preparation-11.0.1.0.0.99.dev14.dist-info/WHEEL
odoo11_addon_stock_picking_package_preparation-11.0.1.0.0.99.dev14.dist-info/top_level.txt
odoo11_addon_stock_picking_package_preparation-11.0.1.0.0.99.dev14.dist-info/RECORD
